oilrad/__init__.py
oilrad/constants.py
oilrad/cts_wavelength/__init__.py
oilrad/cts_wavelength/irradiances.py
oilrad/cts_wavelength/model.py
oilrad/data/MassAbsCoe/Petrobaltic/MAC_0.05.dat
oilrad/data/MassAbsCoe/Petrobaltic/MAC_0.5.dat
oilrad/data/MassAbsCoe/Petrobaltic/MAC_5.0.dat
oilrad/data/MassAbsCoe/Romashkino/MAC_0.05.dat
oilrad/data/MassAbsCoe/Romashkino/MAC_0.25.dat
oilrad/data/MassAbsCoe/Romashkino/MAC_0.5.dat
oilrad/data/MassAbsCoe/Romashkino/MAC_1.5.dat
oilrad/data/MassAbsCoe/Romashkino/MAC_2.5.dat
oilrad/data/MassAbsCoe/Romashkino/MAC_3.5.dat
oilrad/data/MassAbsCoe/Romashkino/MAC_5.0.dat
oilrad/data/SnowSSL/Grenfell1984Fig3BareIceAlbedoJune6.csv
oilrad/data/SnowSSL/Grenfell1984Fig3SnowAlbedoMay21.csv
oilrad/data/SnowSSL/Grenfell2004CloudySpectrum.csv
oilrad/data/SnowSSL/Grenfell2004Fig10aColdSnowAlbedo.csv
oilrad/data/SnowSSL/Light2022Fig2BareIceAlbedo.csv
oilrad/data/SnowSSL/Light2022Fig2ColdSnowAlbedo.csv
oilrad/data/SnowSSL/Light2022Fig2MeltingSnowAlbedo.csv
oilrad/data/SnowSSL/Perovich1990Fig2DrySnowExtinction.csv
oilrad/data/SnowSSL/Perovich1990Fig2MeltingSnowExtinction.csv
oilrad/data/SnowSSL/Perovich1990Fig2SSLExtinction.csv
oilrad/data/SnowSSL/Smith2022Fig20720.csv
oilrad/data/SnowSSL/Smith2022Fig20723.csv
oilrad/data/SnowSSL/Smith2022Fig20724.csv
oilrad/data/SnowSSL/Smith2022Fig20727.csv
oilrad/data/SnowSSL/Verin2022Fig7aColdSnowAlbedo.csv
oilrad/data/Warren_2008_ice_refractive_index.dat
oilrad/integrate.py
oilrad/optics.py
oilrad/six_band/__init__.py
oilrad/six_band/irradiances.py
oilrad/six_band/model.py
oilrad/six_band/top_surface.py
oilrad/solve.py
oilrad/spectra.py
oilrad-2.0.2.dist-info/METADATA
oilrad-2.0.2.dist-info/WHEEL
oilrad-2.0.2.dist-info/RECORD
