Metadata-Version: 2.1
Name: oilrad
Version: 2.0.2
Summary: Two-stream shortwave radiative transfer model for sea ice containing oil droplets.
License: MIT
Author: Joseph Fishlock
Author-email: joseph.fishlock@physics.ox.ax.uk
Requires-Python: >=3.12,<4.0
Classifier: License :: OSI Approved :: MIT License
Classifier: Programming Language :: Python :: 3
Classifier: Programming Language :: Python :: 3.12
Requires-Dist: numpy (>=2.1.0,<3.0.0)
Requires-Dist: scipy (>=1.14.0,<2.0.0)
